{
    "width": 981.0, "height": 1824.0,
    "placeWidth": 48.0, "placeHeight": 60.0,
    "elementsCount": 222,
    "floors": [
        {
            "name": "Cluster 1",
            "prefix": "c1",
            "elementsCount": 74,
            "places": [
                { "host": "c1r12s5", "display": "r12s5", "position": [645.0, 1644.0] },
                { "host": "c1r12s6", "display": "r12s6", "position": [693.0, 1605.0] },
                { "host": "c1r12s7", "display": "r12s7", "position": [741.0, 1644.0] },
                { "host": "c1r11s5", "display": "r11s5", "position": [645.0, 1509.0] },
                { "host": "c1r11s6", "display": "r11s6", "position": [693.0, 1470.0] },
                { "host": "c1r11s7", "display": "r11s7", "position": [741.0, 1509.0] },
                { "host": "c1r11s8", "display": "r11s8", "position": [789.0, 1470.0] },
                { "host": "c1r10s5", "display": "r10s5", "position": [645.0, 1374.0] },
                { "host": "c1r10s6", "display": "r10s6", "position": [693.0, 1335.0] },
                { "host": "c1r10s7", "display": "r10s7", "position": [741.0, 1374.0] },
                { "host": "c1r9s5", "display": "r9s5", "position": [645.0, 1239.0] },
                { "host": "c1r9s6", "display": "r9s6", "position": [693.0, 1200.0] },
                { "host": "c1r9s7", "display": "r9s7", "position": [741.0, 1239.0] },
                { "host": "c1r9s8", "display": "r9s8", "position": [789.0, 1200.0] },
                { "host": "c1r8s2", "display": "r8s2", "position": [144.0, 1104.0] },
                { "host": "c1r8s3", "display": "r8s3", "position": [192.0, 1065.0] },
                { "host": "c1r8s4", "display": "r8s4", "position": [240.0, 1104.0] },
                { "host": "c1r8s5", "display": "r8s5", "position": [645.0, 1104.0] },
                { "host": "c1r8s6", "display": "r8s6", "position": [693.0, 1065.0] },
                { "host": "c1r8s7", "display": "r8s7", "position": [741.0, 1104.0] },
                { "host": "c1r7s1", "display": "r7s1", "position": [96.0, 930.0] },
                { "host": "c1r7s2", "display": "r7s2", "position": [144.0, 969.0] },
                { "host": "c1r7s3", "display": "r7s3", "position": [192.0, 930.0] },
                { "host": "c1r7s4", "display": "r7s4", "position": [240.0, 969.0] },
                { "host": "c1r7s5", "display": "r7s5", "position": [645.0, 969.0] },
                { "host": "c1r7s6", "display": "r7s6", "position": [693.0, 930.0] },
                { "host": "c1r7s7", "display": "r7s7", "position": [741.0, 969.0] },
                { "host": "c1r7s8", "display": "r7s8", "position": [789.0, 930.0] },
                { "host": "c1r6s1", "display": "r6s1", "position": [96.0, 795.0] },
                { "host": "c1r6s2", "display": "r6s2", "position": [144.0, 834.0] },
                { "host": "c1r6s3", "display": "r6s3", "position": [192.0, 795.0] },
                { "host": "c1r6s4", "display": "r6s4", "position": [240.0, 834.0] },
                { "host": "c1r6s5", "display": "r6s5", "position": [645.0, 834.0] },
                { "host": "c1r6s6", "display": "r6s6", "position": [693.0, 795.0] },
                { "host": "c1r6s7", "display": "r6s7", "position": [741.0, 834.0] },
                { "host": "c1r6s8", "display": "r6s8", "position": [789.0, 795.0] },
                { "host": "c1r5s1", "display": "r5s1", "position": [96.0, 660.0] },
                { "host": "c1r5s2", "display": "r5s2", "position": [144.0, 699.0] },
                { "host": "c1r5s3", "display": "r5s3", "position": [192.0, 660.0] },
                { "host": "c1r5s4", "display": "r5s4", "position": [240.0, 699.0] },
                { "host": "c1r5s5", "display": "r5s5", "position": [645.0, 699.0] },
                { "host": "c1r5s6", "display": "r5s6", "position": [693.0, 660.0] },
                { "host": "c1r5s7", "display": "r5s7", "position": [741.0, 699.0] },
                { "host": "c1r5s8", "display": "r5s8", "position": [789.0, 660.0] },
                { "host": "c1r4s1", "display": "r4s1", "position": [96.0, 525.0] },
                { "host": "c1r4s2", "display": "r4s2", "position": [144.0, 564.0] },
                { "host": "c1r4s3", "display": "r4s3", "position": [192.0, 525.0] },
                { "host": "c1r4s4", "display": "r4s4", "position": [240.0, 564.0] },
                { "host": "c1r4s5", "display": "r4s5", "position": [645.0, 564.0] },
                { "host": "c1r4s6", "display": "r4s6", "position": [693.0, 525.0] },
                { "host": "c1r4s7", "display": "r4s7", "position": [741.0, 564.0] },
                { "host": "c1r4s8", "display": "r4s8", "position": [789.0, 525.0] },
                { "host": "c1r3s2", "display": "r3s2", "position": [144.0, 429.0] },
                { "host": "c1r3s3", "display": "r3s3", "position": [192.0, 390.0] },
                { "host": "c1r3s4", "display": "r3s4", "position": [240.0, 429.0] },
                { "host": "c1r3s5", "display": "r3s5", "position": [645.0, 429.0] },
                { "host": "c1r3s6", "display": "r3s6", "position": [693.0, 390.0] },
                { "host": "c1r3s7", "display": "r3s7", "position": [741.0, 429.0] },
                { "host": "c1r2s1", "display": "r2s1", "position": [96.0, 255.0] },
                { "host": "c1r2s2", "display": "r2s2", "position": [144.0, 294.0] },
                { "host": "c1r2s3", "display": "r2s3", "position": [192.0, 255.0] },
                { "host": "c1r2s4", "display": "r2s4", "position": [240.0, 294.0] },
                { "host": "c1r2s5", "display": "r2s5", "position": [645.0, 294.0] },
                { "host": "c1r2s6", "display": "r2s6", "position": [693.0, 255.0] },
                { "host": "c1r2s7", "display": "r2s7", "position": [741.0, 294.0] },
                { "host": "c1r2s8", "display": "r2s8", "position": [789.0, 255.0] },
                { "host": "c1r1s1", "display": "r1s1", "position": [96.0, 120.0] },
                { "host": "c1r1s2", "display": "r1s2", "position": [144.0, 159.0] },
                { "host": "c1r1s3", "display": "r1s3", "position": [192.0, 120.0] },
                { "host": "c1r1s4", "display": "r1s4", "position": [240.0, 159.0] },
                { "host": "c1r1s5", "display": "r1s5", "position": [645.0, 159.0] },
                { "host": "c1r1s6", "display": "r1s6", "position": [693.0, 120.0] },
                { "host": "c1r1s7", "display": "r1s7", "position": [741.0, 159.0] },
                { "host": "c1r1s8", "display": "r1s8", "position": [789.0, 120.0] }
            ],
            "pillars": [
            ]
        },
        {
            "name": "Cluster 2",
            "prefix": "c2",
            "elementsCount": 65,
            "places": [
                { "host": "c2r7s1", "display": "r7s1", "position": [96.0, 930.0] },
                { "host": "c2r7s2", "display": "r7s2", "position": [144.0, 969.0] },
                { "host": "c2r7s3", "display": "r7s3", "position": [192.0, 930.0] },
                { "host": "c2r7s4", "display": "r7s4", "position": [240.0, 969.0] },
                { "host": "c2r7s5", "display": "r7s5", "position": [288.0, 930.0] },
                { "host": "c2r7s6", "display": "r7s6", "position": [645.0, 930.0] },
                { "host": "c2r7s7", "display": "r7s7", "position": [693.0, 969.0] },
                { "host": "c2r7s8", "display": "r7s8", "position": [741.0, 930.0] },
                { "host": "c2r7s9", "display": "r7s9", "position": [789.0, 969.0] },
                { "host": "c2r7s10", "display": "r7s10", "position": [837.0, 930.0] },
                { "host": "c2r6s1", "display": "r6s1", "position": [96.0, 795.0] },
                { "host": "c2r6s2", "display": "r6s2", "position": [144.0, 834.0] },
                { "host": "c2r6s3", "display": "r6s3", "position": [192.0, 795.0] },
                { "host": "c2r6s4", "display": "r6s4", "position": [240.0, 834.0] },
                { "host": "c2r6s5", "display": "r6s5", "position": [288.0, 795.0] },
                { "host": "c2r6s6", "display": "r6s6", "position": [645.0, 795.0] },
                { "host": "c2r6s7", "display": "r6s7", "position": [693.0, 834.0] },
                { "host": "c2r6s8", "display": "r6s8", "position": [741.0, 795.0] },
                { "host": "c2r6s9", "display": "r6s9", "position": [789.0, 834.0] },
                { "host": "c2r6s10", "display": "r6s10", "position": [837.0, 795.0] },
                { "host": "c2r5s2", "display": "r5s2", "position": [144.0, 699.0] },
                { "host": "c2r5s3", "display": "r5s3", "position": [192.0, 660.0] },
                { "host": "c2r5s4", "display": "r5s4", "position": [240.0, 699.0] },
                { "host": "c2r5s5", "display": "r5s5", "position": [288.0, 660.0] },
                { "host": "c2r5s6", "display": "r5s6", "position": [645.0, 660.0] },
                { "host": "c2r5s7", "display": "r5s7", "position": [693.0, 699.0] },
                { "host": "c2r5s8", "display": "r5s8", "position": [741.0, 660.0] },
                { "host": "c2r5s9", "display": "r5s9", "position": [789.0, 699.0] },
                { "host": "c2r4s1", "display": "r4s1", "position": [96.0, 525.0] },
                { "host": "c2r4s2", "display": "r4s2", "position": [144.0, 564.0] },
                { "host": "c2r4s3", "display": "r4s3", "position": [192.0, 525.0] },
                { "host": "c2r4s4", "display": "r4s4", "position": [240.0, 564.0] },
                { "host": "c2r4s5", "display": "r4s5", "position": [288.0, 525.0] },
                { "host": "c2r4s6", "display": "r4s6", "position": [645.0, 525.0] },
                { "host": "c2r4s7", "display": "r4s7", "position": [693.0, 564.0] },
                { "host": "c2r4s8", "display": "r4s8", "position": [741.0, 525.0] },
                { "host": "c2r4s9", "display": "r4s9", "position": [789.0, 564.0] },
                { "host": "c2r4s10", "display": "r4s10", "position": [837.0, 525.0] },
                { "host": "c2r3s1", "display": "r3s1", "position": [96.0, 390.0] },
                { "host": "c2r3s2", "display": "r3s2", "position": [144.0, 429.0] },
                { "host": "c2r3s3", "display": "r3s3", "position": [192.0, 390.0] },
                { "host": "c2r3s4", "display": "r3s4", "position": [240.0, 429.0] },
                { "host": "c2r3s5", "display": "r3s5", "position": [288.0, 390.0] },
                { "host": "c2r3s6", "display": "r3s6", "position": [645.0, 390.0] },
                { "host": "c2r3s7", "display": "r3s7", "position": [693.0, 429.0] },
                { "host": "c2r3s8", "display": "r3s8", "position": [741.0, 390.0] },
                { "host": "c2r3s9", "display": "r3s9", "position": [789.0, 429.0] },
                { "host": "c2r3s10", "display": "r3s10", "position": [837.0, 390.0] },
                { "host": "c2r2s1", "display": "r2s1", "position": [96.0, 255.0] },
                { "host": "c2r2s2", "display": "r2s2", "position": [144.0, 294.0] },
                { "host": "c2r2s3", "display": "r2s3", "position": [192.0, 255.0] },
                { "host": "c2r2s4", "display": "r2s4", "position": [240.0, 294.0] },
                { "host": "c2r2s5", "display": "r2s5", "position": [288.0, 255.0] },
                { "host": "c2r2s6", "display": "r2s6", "position": [645.0, 255.0] },
                { "host": "c2r2s7", "display": "r2s7", "position": [693.0, 294.0] },
                { "host": "c2r2s8", "display": "r2s8", "position": [741.0, 255.0] },
                { "host": "c2r2s9", "display": "r2s9", "position": [789.0, 294.0] },
                { "host": "c2r2s10", "display": "r2s10", "position": [837.0, 255.0] },
                { "host": "c2r1s1", "display": "r1s1", "position": [96.0, 120.0] },
                { "host": "c2r1s2", "display": "r1s2", "position": [144.0, 159.0] },
                { "host": "c2r1s3", "display": "r1s3", "position": [192.0, 120.0] },
                { "host": "c2r1s7", "display": "r1s7", "position": [693.0, 159.0] },
                { "host": "c2r1s8", "display": "r1s8", "position": [741.0, 120.0] },
                { "host": "c2r1s9", "display": "r1s9", "position": [789.0, 159.0] },
                { "host": "c2r1s10", "display": "r1s10", "position": [837.0, 120.0] }
            ],
            "pillars": [
            ]
        },
        {
            "name": "Cluster 3",
            "prefix": "c3",
            "elementsCount": 50,
            "places": [
                { "host": "c3r6s1", "display": "r6s1", "position": [96.0, 834.0] },
                { "host": "c3r6s2", "display": "r6s2", "position": [144.0, 795.0] },
                { "host": "c3r6s3", "display": "r6s3", "position": [192.0, 834.0] },
                { "host": "c3r6s4", "display": "r6s4", "position": [240.0, 795.0] },
                { "host": "c3r5s1", "display": "r5s1", "position": [96.0, 699.0] },
                { "host": "c3r5s2", "display": "r5s2", "position": [144.0, 660.0] },
                { "host": "c3r5s3", "display": "r5s3", "position": [192.0, 699.0] },
                { "host": "c3r5s4", "display": "r5s4", "position": [240.0, 660.0] },
                { "host": "c3r5s7", "display": "r5s7", "position": [693.0, 699.0] },
                { "host": "c3r5s8", "display": "r5s8", "position": [741.0, 660.0] },
                { "host": "c3r5s9", "display": "r5s9", "position": [789.0, 699.0] },
                { "host": "c3r5s10", "display": "r5s10", "position": [837.0, 660.0] },
                { "host": "c3r4s1", "display": "r4s1", "position": [96.0, 564.0] },
                { "host": "c3r4s2", "display": "r4s2", "position": [144.0, 525.0] },
                { "host": "c3r4s3", "display": "r4s3", "position": [192.0, 564.0] },
                { "host": "c3r4s4", "display": "r4s4", "position": [240.0, 525.0] },
                { "host": "c3r4s5", "display": "r4s5", "position": [288.0, 564.0] },
                { "host": "c3r4s7", "display": "r4s7", "position": [693.0, 564.0] },
                { "host": "c3r4s8", "display": "r4s8", "position": [741.0, 525.0] },
                { "host": "c3r4s9", "display": "r4s9", "position": [789.0, 564.0] },
                { "host": "c3r4s10", "display": "r4s10", "position": [837.0, 525.0] },
                { "host": "c3r3s1", "display": "r3s1", "position": [96.0, 429.0] },
                { "host": "c3r3s2", "display": "r3s2", "position": [144.0, 390.0] },
                { "host": "c3r3s3", "display": "r3s3", "position": [192.0, 429.0] },
                { "host": "c3r3s4", "display": "r3s4", "position": [240.0, 390.0] },
                { "host": "c3r3s5", "display": "r3s5", "position": [288.0, 429.0] },
                { "host": "c3r3s6", "display": "r3s6", "position": [336.0, 390.0] },
                { "host": "c3r3s7", "display": "r3s7", "position": [693.0, 429.0] },
                { "host": "c3r3s8", "display": "r3s8", "position": [741.0, 390.0] },
                { "host": "c3r3s9", "display": "r3s9", "position": [789.0, 429.0] },
                { "host": "c3r2s1", "display": "r2s1", "position": [96.0, 294.0] },
                { "host": "c3r2s2", "display": "r2s2", "position": [144.0, 255.0] },
                { "host": "c3r2s3", "display": "r2s3", "position": [192.0, 294.0] },
                { "host": "c3r2s4", "display": "r2s4", "position": [240.0, 255.0] },
                { "host": "c3r2s5", "display": "r2s5", "position": [288.0, 294.0] },
                { "host": "c3r2s6", "display": "r2s6", "position": [336.0, 255.0] },
                { "host": "c3r2s7", "display": "r2s7", "position": [693.0, 294.0] },
                { "host": "c3r2s8", "display": "r2s8", "position": [741.0, 255.0] },
                { "host": "c3r2s9", "display": "r2s9", "position": [789.0, 294.0] },
                { "host": "c3r2s10", "display": "r2s10", "position": [837.0, 255.0] },
                { "host": "c3r1s1", "display": "r1s1", "position": [96.0, 159.0] },
                { "host": "c3r1s2", "display": "r1s2", "position": [144.0, 120.0] },
                { "host": "c3r1s3", "display": "r1s3", "position": [192.0, 159.0] },
                { "host": "c3r1s4", "display": "r1s4", "position": [240.0, 120.0] },
                { "host": "c3r1s5", "display": "r1s5", "position": [288.0, 159.0] },
                { "host": "c3r1s6", "display": "r1s6", "position": [336.0, 120.0] },
                { "host": "c3r1s7", "display": "r1s7", "position": [693.0, 159.0] },
                { "host": "c3r1s8", "display": "r1s8", "position": [741.0, 120.0] },
                { "host": "c3r1s9", "display": "r1s9", "position": [789.0, 159.0] },
                { "host": "c3r1s10", "display": "r1s10", "position": [837.0, 120.0] }
            ],
            "pillars": [
            ]
        }
    ],
    "transitions": [
        {
            "from": 0, "to": 1,
            "remove": [[645.0, 1644.0], [693.0, 1605.0], [741.0, 1644.0], [645.0, 1509.0], [693.0, 1470.0], [741.0, 1509.0], [789.0, 1470.0], [645.0, 1374.0], [693.0, 1335.0], [741.0, 1374.0], [645.0, 1239.0], [693.0, 1200.0], [741.0, 1239.0], [789.0, 1200.0], [144.0, 1104.0], [192.0, 1065.0], [240.0, 1104.0], [645.0, 1104.0], [693.0, 1065.0], [741.0, 1104.0], [645.0, 969.0], [693.0, 930.0], [741.0, 969.0], [789.0, 930.0], [645.0, 834.0], [693.0, 795.0], [741.0, 834.0], [789.0, 795.0], [96.0, 660.0], [645.0, 699.0], [693.0, 660.0], [741.0, 699.0], [789.0, 660.0], [645.0, 564.0], [693.0, 525.0], [741.0, 564.0], [789.0, 525.0], [645.0, 429.0], [693.0, 390.0], [741.0, 429.0], [645.0, 294.0], [693.0, 255.0], [741.0, 294.0], [789.0, 255.0], [240.0, 159.0], [645.0, 159.0], [693.0, 120.0], [741.0, 159.0], [789.0, 120.0]],
            "add": [
                { "host": "c2r7s5", "display": "r7s5", "position": [288.0, 930.0] },
                { "host": "c2r7s6", "display": "r7s6", "position": [645.0, 930.0] },
                { "host": "c2r7s7", "display": "r7s7", "position": [693.0, 969.0] },
                { "host": "c2r7s8", "display": "r7s8", "position": [741.0, 930.0] },
                { "host": "c2r7s9", "display": "r7s9", "position": [789.0, 969.0] },
                { "host": "c2r7s10", "display": "r7s10", "position": [837.0, 930.0] },
                { "host": "c2r6s5", "display": "r6s5", "position": [288.0, 795.0] },
                { "host": "c2r6s6", "display": "r6s6", "position": [645.0, 795.0] },
                { "host": "c2r6s7", "display": "r6s7", "position": [693.0, 834.0] },
                { "host": "c2r6s8", "display": "r6s8", "position": [741.0, 795.0] },
                { "host": "c2r6s9", "display": "r6s9", "position": [789.0, 834.0] },
                { "host": "c2r6s10", "display": "r6s10", "position": [837.0, 795.0] },
                { "host": "c2r5s5", "display": "r5s5", "position": [288.0, 660.0] },
                { "host": "c2r5s6", "display": "r5s6", "position": [645.0, 660.0] },
                { "host": "c2r5s7", "display": "r5s7", "position": [693.0, 699.0] },
                { "host": "c2r5s8", "display": "r5s8", "position": [741.0, 660.0] },
                { "host": "c2r5s9", "display": "r5s9", "position": [789.0, 699.0] },
                { "host": "c2r4s5", "display": "r4s5", "position": [288.0, 525.0] },
                { "host": "c2r4s6", "display": "r4s6", "position": [645.0, 525.0] },
                { "host": "c2r4s7", "display": "r4s7", "position": [693.0, 564.0] },
                { "host": "c2r4s8", "display": "r4s8", "position": [741.0, 525.0] },
                { "host": "c2r4s9", "display": "r4s9", "position": [789.0, 564.0] },
                { "host": "c2r4s10", "display": "r4s10", "position": [837.0, 525.0] },
                { "host": "c2r3s1", "display": "r3s1", "position": [96.0, 390.0] },
                { "host": "c2r3s5", "display": "r3s5", "position": [288.0, 390.0] },
                { "host": "c2r3s6", "display": "r3s6", "position": [645.0, 390.0] },
                { "host": "c2r3s7", "display": "r3s7", "position": [693.0, 429.0] },
                { "host": "c2r3s8", "display": "r3s8", "position": [741.0, 390.0] },
                { "host": "c2r3s9", "display": "r3s9", "position": [789.0, 429.0] },
                { "host": "c2r3s10", "display": "r3s10", "position": [837.0, 390.0] },
                { "host": "c2r2s5", "display": "r2s5", "position": [288.0, 255.0] },
                { "host": "c2r2s6", "display": "r2s6", "position": [645.0, 255.0] },
                { "host": "c2r2s7", "display": "r2s7", "position": [693.0, 294.0] },
                { "host": "c2r2s8", "display": "r2s8", "position": [741.0, 255.0] },
                { "host": "c2r2s9", "display": "r2s9", "position": [789.0, 294.0] },
                { "host": "c2r2s10", "display": "r2s10", "position": [837.0, 255.0] },
                { "host": "c2r1s7", "display": "r1s7", "position": [693.0, 159.0] },
                { "host": "c2r1s8", "display": "r1s8", "position": [741.0, 120.0] },
                { "host": "c2r1s9", "display": "r1s9", "position": [789.0, 159.0] },
                { "host": "c2r1s10", "display": "r1s10", "position": [837.0, 120.0] }
            ],
            "update": [],
            "pillarRemove": [],
            "pillarAdd": []
        },
        {
            "from": 0, "to": 2,
            "remove": [[645.0, 1644.0], [693.0, 1605.0], [741.0, 1644.0], [645.0, 1509.0], [693.0, 1470.0], [741.0, 1509.0], [789.0, 1470.0], [645.0, 1374.0], [693.0, 1335.0], [741.0, 1374.0], [645.0, 1239.0], [693.0, 1200.0], [741.0, 1239.0], [789.0, 1200.0], [144.0, 1104.0], [192.0, 1065.0], [240.0, 1104.0], [645.0, 1104.0], [693.0, 1065.0], [741.0, 1104.0], [96.0, 930.0], [144.0, 969.0], [192.0, 930.0], [240.0, 969.0], [645.0, 969.0], [693.0, 930.0], [741.0, 969.0], [789.0, 930.0], [96.0, 795.0], [144.0, 834.0], [192.0, 795.0], [240.0, 834.0], [645.0, 834.0], [693.0, 795.0], [741.0, 834.0], [789.0, 795.0], [96.0, 660.0], [144.0, 699.0], [192.0, 660.0], [240.0, 699.0], [645.0, 699.0], [693.0, 660.0], [741.0, 699.0], [789.0, 660.0], [96.0, 525.0], [144.0, 564.0], [192.0, 525.0], [240.0, 564.0], [645.0, 564.0], [693.0, 525.0], [741.0, 564.0], [789.0, 525.0], [144.0, 429.0], [192.0, 390.0], [240.0, 429.0], [645.0, 429.0], [693.0, 390.0], [741.0, 429.0], [96.0, 255.0], [144.0, 294.0], [192.0, 255.0], [240.0, 294.0], [645.0, 294.0], [693.0, 255.0], [741.0, 294.0], [789.0, 255.0], [96.0, 120.0], [144.0, 159.0], [192.0, 120.0], [240.0, 159.0], [645.0, 159.0], [693.0, 120.0], [741.0, 159.0], [789.0, 120.0]],
            "add": [
                { "host": "c3r6s1", "display": "r6s1", "position": [96.0, 834.0] },
                { "host": "c3r6s2", "display": "r6s2", "position": [144.0, 795.0] },
                { "host": "c3r6s3", "display": "r6s3", "position": [192.0, 834.0] },
                { "host": "c3r6s4", "display": "r6s4", "position": [240.0, 795.0] },
                { "host": "c3r5s1", "display": "r5s1", "position": [96.0, 699.0] },
                { "host": "c3r5s2", "display": "r5s2", "position": [144.0, 660.0] },
                { "host": "c3r5s3", "display": "r5s3", "position": [192.0, 699.0] },
                { "host": "c3r5s4", "display": "r5s4", "position": [240.0, 660.0] },
                { "host": "c3r5s7", "display": "r5s7", "position": [693.0, 699.0] },
                { "host": "c3r5s8", "display": "r5s8", "position": [741.0, 660.0] },
                { "host": "c3r5s9", "display": "r5s9", "position": [789.0, 699.0] },
                { "host": "c3r5s10", "display": "r5s10", "position": [837.0, 660.0] },
                { "host": "c3r4s1", "display": "r4s1", "position": [96.0, 564.0] },
                { "host": "c3r4s2", "display": "r4s2", "position": [144.0, 525.0] },
                { "host": "c3r4s3", "display": "r4s3", "position": [192.0, 564.0] },
                { "host": "c3r4s4", "display": "r4s4", "position": [240.0, 525.0] },
                { "host": "c3r4s5", "display": "r4s5", "position": [288.0, 564.0] },
                { "host": "c3r4s7", "display": "r4s7", "position": [693.0, 564.0] },
                { "host": "c3r4s8", "display": "r4s8", "position": [741.0, 525.0] },
                { "host": "c3r4s9", "display": "r4s9", "position": [789.0, 564.0] },
                { "host": "c3r4s10", "display": "r4s10", "position": [837.0, 525.0] },
                { "host": "c3r3s1", "display": "r3s1", "position": [96.0, 429.0] },
                { "host": "c3r3s2", "display": "r3s2", "position": [144.0, 390.0] },
                { "host": "c3r3s3", "display": "r3s3", "position": [192.0, 429.0] },
                { "host": "c3r3s4", "display": "r3s4", "position": [240.0, 390.0] },
                { "host": "c3r3s5", "display": "r3s5", "position": [288.0, 429.0] },
                { "host": "c3r3s6", "display": "r3s6", "position": [336.0, 390.0] },
                { "host": "c3r3s7", "display": "r3s7", "position": [693.0, 429.0] },
                { "host": "c3r3s8", "display": "r3s8", "position": [741.0, 390.0] },
                { "host": "c3r3s9", "display": "r3s9", "position": [789.0, 429.0] },
                { "host": "c3r2s1", "display": "r2s1", "position": [96.0, 294.0] },
                { "host": "c3r2s2", "display": "r2s2", "position": [144.0, 255.0] },
                { "host": "c3r2s3", "display": "r2s3", "position": [192.0, 294.0] },
                { "host": "c3r2s4", "display": "r2s4", "position": [240.0, 255.0] },
                { "host": "c3r2s5", "display": "r2s5", "position": [288.0, 294.0] },
                { "host": "c3r2s6", "display": "r2s6", "position": [336.0, 255.0] },
                { "host": "c3r2s7", "display": "r2s7", "position": [693.0, 294.0] },
                { "host": "c3r2s8", "display": "r2s8", "position": [741.0, 255.0] },
                { "host": "c3r2s9", "display": "r2s9", "position": [789.0, 294.0] },
                { "host": "c3r2s10", "display": "r2s10", "position": [837.0, 255.0] },
                { "host": "c3r1s1", "display": "r1s1", "position": [96.0, 159.0] },
                { "host": "c3r1s2", "display": "r1s2", "position": [144.0, 120.0] },
                { "host": "c3r1s3", "display": "r1s3", "position": [192.0, 159.0] },
                { "host": "c3r1s4", "display": "r1s4", "position": [240.0, 120.0] },
                { "host": "c3r1s5", "display": "r1s5", "position": [288.0, 159.0] },
                { "host": "c3r1s6", "display": "r1s6", "position": [336.0, 120.0] },
                { "host": "c3r1s7", "display": "r1s7", "position": [693.0, 159.0] },
                { "host": "c3r1s8", "display": "r1s8", "position": [741.0, 120.0] },
                { "host": "c3r1s9", "display": "r1s9", "position": [789.0, 159.0] },
                { "host": "c3r1s10", "display": "r1s10", "position": [837.0, 120.0] }
            ],
            "update": [],
            "pillarRemove": [],
            "pillarAdd": []
        },
        {
            "from": 1, "to": 0,
            "remove": [[288.0, 930.0], [645.0, 930.0], [693.0, 969.0], [741.0, 930.0], [789.0, 969.0], [837.0, 930.0], [288.0, 795.0], [645.0, 795.0], [693.0, 834.0], [741.0, 795.0], [789.0, 834.0], [837.0, 795.0], [288.0, 660.0], [645.0, 660.0], [693.0, 699.0], [741.0, 660.0], [789.0, 699.0], [288.0, 525.0], [645.0, 525.0], [693.0, 564.0], [741.0, 525.0], [789.0, 564.0], [837.0, 525.0], [96.0, 390.0], [288.0, 390.0], [645.0, 390.0], [693.0, 429.0], [741.0, 390.0], [789.0, 429.0], [837.0, 390.0], [288.0, 255.0], [645.0, 255.0], [693.0, 294.0], [741.0, 255.0], [789.0, 294.0], [837.0, 255.0], [693.0, 159.0], [741.0, 120.0], [789.0, 159.0], [837.0, 120.0]],
            "add": [
                { "host": "c1r12s5", "display": "r12s5", "position": [645.0, 1644.0] },
                { "host": "c1r12s6", "display": "r12s6", "position": [693.0, 1605.0] },
                { "host": "c1r12s7", "display": "r12s7", "position": [741.0, 1644.0] },
                { "host": "c1r11s5", "display": "r11s5", "position": [645.0, 1509.0] },
                { "host": "c1r11s6", "display": "r11s6", "position": [693.0, 1470.0] },
                { "host": "c1r11s7", "display": "r11s7", "position": [741.0, 1509.0] },
                { "host": "c1r11s8", "display": "r11s8", "position": [789.0, 1470.0] },
                { "host": "c1r10s5", "display": "r10s5", "position": [645.0, 1374.0] },
                { "host": "c1r10s6", "display": "r10s6", "position": [693.0, 1335.0] },
                { "host": "c1r10s7", "display": "r10s7", "position": [741.0, 1374.0] },
                { "host": "c1r9s5", "display": "r9s5", "position": [645.0, 1239.0] },
                { "host": "c1r9s6", "display": "r9s6", "position": [693.0, 1200.0] },
                { "host": "c1r9s7", "display": "r9s7", "position": [741.0, 1239.0] },
                { "host": "c1r9s8", "display": "r9s8", "position": [789.0, 1200.0] },
                { "host": "c1r8s2", "display": "r8s2", "position": [144.0, 1104.0] },
                { "host": "c1r8s3", "display": "r8s3", "position": [192.0, 1065.0] },
                { "host": "c1r8s4", "display": "r8s4", "position": [240.0, 1104.0] },
                { "host": "c1r8s5", "display": "r8s5", "position": [645.0, 1104.0] },
                { "host": "c1r8s6", "display": "r8s6", "position": [693.0, 1065.0] },
                { "host": "c1r8s7", "display": "r8s7", "position": [741.0, 1104.0] },
                { "host": "c1r7s5", "display": "r7s5", "position": [645.0, 969.0] },
                { "host": "c1r7s6", "display": "r7s6", "position": [693.0, 930.0] },
                { "host": "c1r7s7", "display": "r7s7", "position": [741.0, 969.0] },
                { "host": "c1r7s8", "display": "r7s8", "position": [789.0, 930.0] },
                { "host": "c1r6s5", "display": "r6s5", "position": [645.0, 834.0] },
                { "host": "c1r6s6", "display": "r6s6", "position": [693.0, 795.0] },
                { "host": "c1r6s7", "display": "r6s7", "position": [741.0, 834.0] },
                { "host": "c1r6s8", "display": "r6s8", "position": [789.0, 795.0] },
                { "host": "c1r5s1", "display": "r5s1", "position": [96.0, 660.0] },
                { "host": "c1r5s5", "display": "r5s5", "position": [645.0, 699.0] },
                { "host": "c1r5s6", "display": "r5s6", "position": [693.0, 660.0] },
                { "host": "c1r5s7", "display": "r5s7", "position": [741.0, 699.0] },
                { "host": "c1r5s8", "display": "r5s8", "position": [789.0, 660.0] },
                { "host": "c1r4s5", "display": "r4s5", "position": [645.0, 564.0] },
                { "host": "c1r4s6", "display": "r4s6", "position": [693.0, 525.0] },
                { "host": "c1r4s7", "display": "r4s7", "position": [741.0, 564.0] },
                { "host": "c1r4s8", "display": "r4s8", "position": [789.0, 525.0] },
                { "host": "c1r3s5", "display": "r3s5", "position": [645.0, 429.0] },
                { "host": "c1r3s6", "display": "r3s6", "position": [693.0, 390.0] },
                { "host": "c1r3s7", "display": "r3s7", "position": [741.0, 429.0] },
                { "host": "c1r2s5", "display": "r2s5", "position": [645.0, 294.0] },
                { "host": "c1r2s6", "display": "r2s6", "position": [693.0, 255.0] },
                { "host": "c1r2s7", "display": "r2s7", "position": [741.0, 294.0] },
                { "host": "c1r2s8", "display": "r2s8", "position": [789.0, 255.0] },
                { "host": "c1r1s4", "display": "r1s4", "position": [240.0, 159.0] },
                { "host": "c1r1s5", "display": "r1s5", "position": [645.0, 159.0] },
                { "host": "c1r1s6", "display": "r1s6", "position": [693.0, 120.0] },
                { "host": "c1r1s7", "display": "r1s7", "position": [741.0, 159.0] },
                { "host": "c1r1s8", "display": "r1s8", "position": [789.0, 120.0] }
            ],
            "update": [],
            "pillarRemove": [],
            "pillarAdd": []
        },
        {
            "from": 1, "to": 2,
            "remove": [[96.0, 930.0], [144.0, 969.0], [192.0, 930.0], [240.0, 969.0], [288.0, 930.0], [645.0, 930.0], [693.0, 969.0], [741.0, 930.0], [789.0, 969.0], [837.0, 930.0], [96.0, 795.0], [144.0, 834.0], [192.0, 795.0], [240.0, 834.0], [288.0, 795.0], [645.0, 795.0], [693.0, 834.0], [741.0, 795.0], [789.0, 834.0], [837.0, 795.0], [144.0, 699.0], [192.0, 660.0], [240.0, 699.0], [288.0, 660.0], [645.0, 660.0], [96.0, 525.0], [144.0, 564.0], [192.0, 525.0], [240.0, 564.0], [288.0, 525.0], [645.0, 525.0], [96.0, 390.0], [144.0, 429.0], [192.0, 390.0], [240.0, 429.0], [288.0, 390.0], [645.0, 390.0], [837.0, 390.0], [96.0, 255.0], [144.0, 294.0], [192.0, 255.0], [240.0, 294.0], [288.0, 255.0], [645.0, 255.0], [96.0, 120.0], [144.0, 159.0], [192.0, 120.0]],
            "add": [
                { "host": "c3r6s1", "display": "r6s1", "position": [96.0, 834.0] },
                { "host": "c3r6s2", "display": "r6s2", "position": [144.0, 795.0] },
                { "host": "c3r6s3", "display": "r6s3", "position": [192.0, 834.0] },
                { "host": "c3r6s4", "display": "r6s4", "position": [240.0, 795.0] },
                { "host": "c3r5s1", "display": "r5s1", "position": [96.0, 699.0] },
                { "host": "c3r5s2", "display": "r5s2", "position": [144.0, 660.0] },
                { "host": "c3r5s3", "display": "r5s3", "position": [192.0, 699.0] },
                { "host": "c3r5s4", "display": "r5s4", "position": [240.0, 660.0] },
                { "host": "c3r5s10", "display": "r5s10", "position": [837.0, 660.0] },
                { "host": "c3r4s1", "display": "r4s1", "position": [96.0, 564.0] },
                { "host": "c3r4s2", "display": "r4s2", "position": [144.0, 525.0] },
                { "host": "c3r4s3", "display": "r4s3", "position": [192.0, 564.0] },
                { "host": "c3r4s4", "display": "r4s4", "position": [240.0, 525.0] },
                { "host": "c3r4s5", "display": "r4s5", "position": [288.0, 564.0] },
                { "host": "c3r3s1", "display": "r3s1", "position": [96.0, 429.0] },
                { "host": "c3r3s2", "display": "r3s2", "position": [144.0, 390.0] },
                { "host": "c3r3s3", "display": "r3s3", "position": [192.0, 429.0] },
                { "host": "c3r3s4", "display": "r3s4", "position": [240.0, 390.0] },
                { "host": "c3r3s5", "display": "r3s5", "position": [288.0, 429.0] },
                { "host": "c3r3s6", "display": "r3s6", "position": [336.0, 390.0] },
                { "host": "c3r2s1", "display": "r2s1", "position": [96.0, 294.0] },
                { "host": "c3r2s2", "display": "r2s2", "position": [144.0, 255.0] },
                { "host": "c3r2s3", "display": "r2s3", "position": [192.0, 294.0] },
                { "host": "c3r2s4", "display": "r2s4", "position": [240.0, 255.0] },
                { "host": "c3r2s5", "display": "r2s5", "position": [288.0, 294.0] },
                { "host": "c3r2s6", "display": "r2s6", "position": [336.0, 255.0] },
                { "host": "c3r1s1", "display": "r1s1", "position": [96.0, 159.0] },
                { "host": "c3r1s2", "display": "r1s2", "position": [144.0, 120.0] },
                { "host": "c3r1s3", "display": "r1s3", "position": [192.0, 159.0] },
                { "host": "c3r1s4", "display": "r1s4", "position": [240.0, 120.0] },
                { "host": "c3r1s5", "display": "r1s5", "position": [288.0, 159.0] },
                { "host": "c3r1s6", "display": "r1s6", "position": [336.0, 120.0] }
            ],
            "update": [],
            "pillarRemove": [],
            "pillarAdd": []
        },
        {
            "from": 2, "to": 0,
            "remove": [[96.0, 834.0], [144.0, 795.0], [192.0, 834.0], [240.0, 795.0], [96.0, 699.0], [144.0, 660.0], [192.0, 699.0], [240.0, 660.0], [693.0, 699.0], [741.0, 660.0], [789.0, 699.0], [837.0, 660.0], [96.0, 564.0], [144.0, 525.0], [192.0, 564.0], [240.0, 525.0], [288.0, 564.0], [693.0, 564.0], [741.0, 525.0], [789.0, 564.0], [837.0, 525.0], [96.0, 429.0], [144.0, 390.0], [192.0, 429.0], [240.0, 390.0], [288.0, 429.0], [336.0, 390.0], [693.0, 429.0], [741.0, 390.0], [789.0, 429.0], [96.0, 294.0], [144.0, 255.0], [192.0, 294.0], [240.0, 255.0], [288.0, 294.0], [336.0, 255.0], [693.0, 294.0], [741.0, 255.0], [789.0, 294.0], [837.0, 255.0], [96.0, 159.0], [144.0, 120.0], [192.0, 159.0], [240.0, 120.0], [288.0, 159.0], [336.0, 120.0], [693.0, 159.0], [741.0, 120.0], [789.0, 159.0], [837.0, 120.0]],
            "add": [
                { "host": "c1r12s5", "display": "r12s5", "position": [645.0, 1644.0] },
                { "host": "c1r12s6", "display": "r12s6", "position": [693.0, 1605.0] },
                { "host": "c1r12s7", "display": "r12s7", "position": [741.0, 1644.0] },
                { "host": "c1r11s5", "display": "r11s5", "position": [645.0, 1509.0] },
                { "host": "c1r11s6", "display": "r11s6", "position": [693.0, 1470.0] },
                { "host": "c1r11s7", "display": "r11s7", "position": [741.0, 1509.0] },
                { "host": "c1r11s8", "display": "r11s8", "position": [789.0, 1470.0] },
                { "host": "c1r10s5", "display": "r10s5", "position": [645.0, 1374.0] },
                { "host": "c1r10s6", "display": "r10s6", "position": [693.0, 1335.0] },
                { "host": "c1r10s7", "display": "r10s7", "position": [741.0, 1374.0] },
                { "host": "c1r9s5", "display": "r9s5", "position": [645.0, 1239.0] },
                { "host": "c1r9s6", "display": "r9s6", "position": [693.0, 1200.0] },
                { "host": "c1r9s7", "display": "r9s7", "position": [741.0, 1239.0] },
                { "host": "c1r9s8", "display": "r9s8", "position": [789.0, 1200.0] },
                { "host": "c1r8s2", "display": "r8s2", "position": [144.0, 1104.0] },
                { "host": "c1r8s3", "display": "r8s3", "position": [192.0, 1065.0] },
                { "host": "c1r8s4", "display": "r8s4", "position": [240.0, 1104.0] },
                { "host": "c1r8s5", "display": "r8s5", "position": [645.0, 1104.0] },
                { "host": "c1r8s6", "display": "r8s6", "position": [693.0, 1065.0] },
                { "host": "c1r8s7", "display": "r8s7", "position": [741.0, 1104.0] },
                { "host": "c1r7s1", "display": "r7s1", "position": [96.0, 930.0] },
                { "host": "c1r7s2", "display": "r7s2", "position": [144.0, 969.0] },
                { "host": "c1r7s3", "display": "r7s3", "position": [192.0, 930.0] },
                { "host": "c1r7s4", "display": "r7s4", "position": [240.0, 969.0] },
                { "host": "c1r7s5", "display": "r7s5", "position": [645.0, 969.0] },
                { "host": "c1r7s6", "display": "r7s6", "position": [693.0, 930.0] },
                { "host": "c1r7s7", "display": "r7s7", "position": [741.0, 969.0] },
                { "host": "c1r7s8", "display": "r7s8", "position": [789.0, 930.0] },
                { "host": "c1r6s1", "display": "r6s1", "position": [96.0, 795.0] },
                { "host": "c1r6s2", "display": "r6s2", "position": [144.0, 834.0] },
                { "host": "c1r6s3", "display": "r6s3", "position": [192.0, 795.0] },
                { "host": "c1r6s4", "display": "r6s4", "position": [240.0, 834.0] },
                { "host": "c1r6s5", "display": "r6s5", "position": [645.0, 834.0] },
                { "host": "c1r6s6", "display": "r6s6", "position": [693.0, 795.0] },
                { "host": "c1r6s7", "display": "r6s7", "position": [741.0, 834.0] },
                { "host": "c1r6s8", "display": "r6s8", "position": [789.0, 795.0] },
                { "host": "c1r5s1", "display": "r5s1", "position": [96.0, 660.0] },
                { "host": "c1r5s2", "display": "r5s2", "position": [144.0, 699.0] },
                { "host": "c1r5s3", "display": "r5s3", "position": [192.0, 660.0] },
                { "host": "c1r5s4", "display": "r5s4", "position": [240.0, 699.0] },
                { "host": "c1r5s5", "display": "r5s5", "position": [645.0, 699.0] },
                { "host": "c1r5s6", "display": "r5s6", "position": [693.0, 660.0] },
                { "host": "c1r5s7", "display": "r5s7", "position": [741.0, 699.0] },
                { "host": "c1r5s8", "display": "r5s8", "position": [789.0, 660.0] },
                { "host": "c1r4s1", "display": "r4s1", "position": [96.0, 525.0] },
                { "host": "c1r4s2", "display": "r4s2", "position": [144.0, 564.0] },
                { "host": "c1r4s3", "display": "r4s3", "position": [192.0, 525.0] },
                { "host": "c1r4s4", "display": "r4s4", "position": [240.0, 564.0] },
                { "host": "c1r4s5", "display": "r4s5", "position": [645.0, 564.0] },
                { "host": "c1r4s6", "display": "r4s6", "position": [693.0, 525.0] },
                { "host": "c1r4s7", "display": "r4s7", "position": [741.0, 564.0] },
                { "host": "c1r4s8", "display": "r4s8", "position": [789.0, 525.0] },
                { "host": "c1r3s2", "display": "r3s2", "position": [144.0, 429.0] },
                { "host": "c1r3s3", "display": "r3s3", "position": [192.0, 390.0] },
                { "host": "c1r3s4", "display": "r3s4", "position": [240.0, 429.0] },
                { "host": "c1r3s5", "display": "r3s5", "position": [645.0, 429.0] },
                { "host": "c1r3s6", "display": "r3s6", "position": [693.0, 390.0] },
                { "host": "c1r3s7", "display": "r3s7", "position": [741.0, 429.0] },
                { "host": "c1r2s1", "display": "r2s1", "position": [96.0, 255.0] },
                { "host": "c1r2s2", "display": "r2s2", "position": [144.0, 294.0] },
                { "host": "c1r2s3", "display": "r2s3", "position": [192.0, 255.0] },
                { "host": "c1r2s4", "display": "r2s4", "position": [240.0, 294.0] },
                { "host": "c1r2s5", "display": "r2s5", "position": [645.0, 294.0] },
                { "host": "c1r2s6", "display": "r2s6", "position": [693.0, 255.0] },
                { "host": "c1r2s7", "display": "r2s7", "position": [741.0, 294.0] },
                { "host": "c1r2s8", "display": "r2s8", "position": [789.0, 255.0] },
                { "host": "c1r1s1", "display": "r1s1", "position": [96.0, 120.0] },
                { "host": "c1r1s2", "display": "r1s2", "position": [144.0, 159.0] },
                { "host": "c1r1s3", "display": "r1s3", "position": [192.0, 120.0] },
                { "host": "c1r1s4", "display": "r1s4", "position": [240.0, 159.0] },
                { "host": "c1r1s5", "display": "r1s5", "position": [645.0, 159.0] },
                { "host": "c1r1s6", "display": "r1s6", "position": [693.0, 120.0] },
                { "host": "c1r1s7", "display": "r1s7", "position": [741.0, 159.0] },
                { "host": "c1r1s8", "display": "r1s8", "position": [789.0, 120.0] }
            ],
            "update": [],
            "pillarRemove": [],
            "pillarAdd": []
        },
        {
            "from": 2, "to": 1,
            "remove": [[96.0, 834.0], [144.0, 795.0], [192.0, 834.0], [240.0, 795.0], [96.0, 699.0], [144.0, 660.0], [192.0, 699.0], [240.0, 660.0], [837.0, 660.0], [96.0, 564.0], [144.0, 525.0], [192.0, 564.0], [240.0, 525.0], [288.0, 564.0], [96.0, 429.0], [144.0, 390.0], [192.0, 429.0], [240.0, 390.0], [288.0, 429.0], [336.0, 390.0], [96.0, 294.0], [144.0, 255.0], [192.0, 294.0], [240.0, 255.0], [288.0, 294.0], [336.0, 255.0], [96.0, 159.0], [144.0, 120.0], [192.0, 159.0], [240.0, 120.0], [288.0, 159.0], [336.0, 120.0]],
            "add": [
                { "host": "c2r7s1", "display": "r7s1", "position": [96.0, 930.0] },
                { "host": "c2r7s2", "display": "r7s2", "position": [144.0, 969.0] },
                { "host": "c2r7s3", "display": "r7s3", "position": [192.0, 930.0] },
                { "host": "c2r7s4", "display": "r7s4", "position": [240.0, 969.0] },
                { "host": "c2r7s5", "display": "r7s5", "position": [288.0, 930.0] },
                { "host": "c2r7s6", "display": "r7s6", "position": [645.0, 930.0] },
                { "host": "c2r7s7", "display": "r7s7", "position": [693.0, 969.0] },
                { "host": "c2r7s8", "display": "r7s8", "position": [741.0, 930.0] },
                { "host": "c2r7s9", "display": "r7s9", "position": [789.0, 969.0] },
                { "host": "c2r7s10", "display": "r7s10", "position": [837.0, 930.0] },
                { "host": "c2r6s1", "display": "r6s1", "position": [96.0, 795.0] },
                { "host": "c2r6s2", "display": "r6s2", "position": [144.0, 834.0] },
                { "host": "c2r6s3", "display": "r6s3", "position": [192.0, 795.0] },
                { "host": "c2r6s4", "display": "r6s4", "position": [240.0, 834.0] },
                { "host": "c2r6s5", "display": "r6s5", "position": [288.0, 795.0] },
                { "host": "c2r6s6", "display": "r6s6", "position": [645.0, 795.0] },
                { "host": "c2r6s7", "display": "r6s7", "position": [693.0, 834.0] },
                { "host": "c2r6s8", "display": "r6s8", "position": [741.0, 795.0] },
                { "host": "c2r6s9", "display": "r6s9", "position": [789.0, 834.0] },
                { "host": "c2r6s10", "display": "r6s10", "position": [837.0, 795.0] },
                { "host": "c2r5s2", "display": "r5s2", "position": [144.0, 699.0] },
                { "host": "c2r5s3", "display": "r5s3", "position": [192.0, 660.0] },
                { "host": "c2r5s4", "display": "r5s4", "position": [240.0, 699.0] },
                { "host": "c2r5s5", "display": "r5s5", "position": [288.0, 660.0] },
                { "host": "c2r5s6", "display": "r5s6", "position": [645.0, 660.0] },
                { "host": "c2r4s1", "display": "r4s1", "position": [96.0, 525.0] },
                { "host": "c2r4s2", "display": "r4s2", "position": [144.0, 564.0] },
                { "host": "c2r4s3", "display": "r4s3", "position": [192.0, 525.0] },
                { "host": "c2r4s4", "display": "r4s4", "position": [240.0, 564.0] },
                { "host": "c2r4s5", "display": "r4s5", "position": [288.0, 525.0] },
                { "host": "c2r4s6", "display": "r4s6", "position": [645.0, 525.0] },
                { "host": "c2r3s1", "display": "r3s1", "position": [96.0, 390.0] },
                { "host": "c2r3s2", "display": "r3s2", "position": [144.0, 429.0] },
                { "host": "c2r3s3", "display": "r3s3", "position": [192.0, 390.0] },
                { "host": "c2r3s4", "display": "r3s4", "position": [240.0, 429.0] },
                { "host": "c2r3s5", "display": "r3s5", "position": [288.0, 390.0] },
                { "host": "c2r3s6", "display": "r3s6", "position": [645.0, 390.0] },
                { "host": "c2r3s10", "display": "r3s10", "position": [837.0, 390.0] },
                { "host": "c2r2s1", "display": "r2s1", "position": [96.0, 255.0] },
                { "host": "c2r2s2", "display": "r2s2", "position": [144.0, 294.0] },
                { "host": "c2r2s3", "display": "r2s3", "position": [192.0, 255.0] },
                { "host": "c2r2s4", "display": "r2s4", "position": [240.0, 294.0] },
                { "host": "c2r2s5", "display": "r2s5", "position": [288.0, 255.0] },
                { "host": "c2r2s6", "display": "r2s6", "position": [645.0, 255.0] },
                { "host": "c2r1s1", "display": "r1s1", "position": [96.0, 120.0] },
                { "host": "c2r1s2", "display": "r1s2", "position": [144.0, 159.0] },
                { "host": "c2r1s3", "display": "r1s3", "position": [192.0, 120.0] }
            ],
            "update": [],
            "pillarRemove": [],
            "pillarAdd": []
        }
    ]
}
